mirrulations/__init__.py
mirrulations/cli.py
mirrulations/csv.py
mirrulations/fetch.py
mirrulations/py.typed
mirrulations-0.1.2.dist-info/licenses/LICENSE
mirrulations-0.1.2.dist-info/WHEEL
mirrulations-0.1.2.dist-info/entry_points.txt
mirrulations-0.1.2.dist-info/METADATA
mirrulations-0.1.2.dist-info/RECORD
