Metadata-Version: 2.4
Name: mirrulations
Version: 0.1.2
Summary: A utility tool for accessing data from the Mirrulations dataset.
Author: Jay Qi, Ben Coleman
Author-email: Jay Qi <jayqi@users.noreply.github.com>, Ben Coleman <colemanb@moravian.edu>
License-Expression: MIT
License-File: LICENSE
Requires-Dist: boto3
Requires-Dist: click
Requires-Dist: tqdm
Requires-Python: >=3.9
